setup.py
django_ip2country.egg-info/PKG-INFO
django_ip2country.egg-info/SOURCES.txt
django_ip2country.egg-info/dependency_links.txt
django_ip2country.egg-info/top_level.txt
ip2country/__init__.py
ip2country/admin.py
ip2country/context_processors.py
ip2country/models.py
ip2country/tests.py
ip2country/urls.py
ip2country/utils.py
ip2country/views.py
ip2country/fixtures/__init__.py
ip2country/fixtures/data.json
ip2country/migrations/__init__.py
ip2country/templatetags/__init__.py
ip2country/templatetags/i2c.py