Metadata-Version: 1.1
Name: django-ip2country
Version: 1.0.4
Summary: Find User Country From IP Address
Home-page: https://github.com/sauditore/django-ip2country
Author: saeed Auditore
Author-email: saeed.auditore@gmail.com
License: WTFPL
Keywords: django ip2country ipcountry
Platform: UNKNOWN
Classifier: Development Status :: 3 - Alpha
Classifier: Topic :: Utilities
